directadmin/__init__.py
directadmin/api.py
directadmin_client-0.0.1.dist-info/LICENSE.md
directadmin_client-0.0.1.dist-info/METADATA
directadmin_client-0.0.1.dist-info/WHEEL
directadmin_client-0.0.1.dist-info/top_level.txt
directadmin_client-0.0.1.dist-info/RECORD
